retinapy/__init__.py
retinapy/_logging.py
retinapy/dataset.py
retinapy/mea.py
retinapy/models.py
retinapy/nn.py
retinapy/spikedistancefield.py
retinapy/spikeprediction.py
retinapy/train.py
retinapy/vis.py
retinapy-0.0.1.dev9.dist-info/METADATA
retinapy-0.0.1.dev9.dist-info/WHEEL
retinapy-0.0.1.dev9.dist-info/top_level.txt
retinapy-0.0.1.dev9.dist-info/RECORD
